.VERSION
AUTHORS.rst
CONTRIBUTING.rst
HISTORY.rst
LICENSE
MANIFEST.in
Pipfile
Pipfile.lock
README.rst
USAGE.rst
dev-requirements.txt
requirements.txt
setup.cfg
setup.py
docs/Makefile
docs/authors.rst
docs/conf.py
docs/contributing.rst
docs/history.rst
docs/index.rst
docs/installation.rst
docs/modules.rst
docs/readme.rst
docs/slacksound.rst
docs/usage.rst
slacksound/.VERSION
slacksound/__init__.py
slacksound/_version.py
slacksound/slackapi.py
slacksound/slacksound.py
slacksound/slacksoundexceptions.py
slacksound/spotifyclient.py
slacksound.egg-info/PKG-INFO
slacksound.egg-info/SOURCES.txt
slacksound.egg-info/dependency_links.txt
slacksound.egg-info/entry_points.txt
slacksound.egg-info/not-zip-safe
slacksound.egg-info/requires.txt
slacksound.egg-info/top_level.txt