Metadata-Version: 1.1
Name: slacksound
Version: 0.1.1
Summary: Create playlists democratically by reactions in Slack
Home-page: https://github.com/wefner/slacksound
Author: Oriol Fabregas
Author-email: fabregas.oriol@gmail.com
License: MIT
Keywords: slacksound
Platform: UNKNOWN
Classifier: Development Status :: 4 - Beta
Classifier: Intended Audience :: Developers
Classifier: License :: OSI Approved :: MIT License
Classifier: Natural Language :: English
Classifier: Programming Language :: Python
